xsigma.py
xsigma-1.2.0.dev0.dist-info/DELVEWHEEL
xsigma-1.2.0.dev0.dist-info/METADATA
xsigma-1.2.0.dev0.dist-info/RECORD
xsigma-1.2.0.dev0.dist-info/top_level.txt
xsigma-1.2.0.dev0.dist-info/WHEEL
xsigma.libs/Analytics-1.0-a059852eca0ebda4675738d0081986bc.dll
xsigma.libs/Core-1.0-0c31a66ec7f176db38502b2ec370e29a.dll
xsigma.libs/Market-1.0-29b8e40ae72873ee73bca5e102720921.dll
xsigma.libs/Math-1.0-51a670b9e7256d27acfccfec7d0ef711.dll
xsigma.libs/msvcp140-5ea7d75697589d2c59baa7d639180e95.dll
xsigma.libs/PDE-1.0-3ae851674556134fad287ea5fc44e5b4.dll
xsigma.libs/Random-1.0-1efaa556eec9973e80ff670101d96965.dll
xsigma.libs/Serialization-1.0-33411280baf8db0e1c697395dbec6e14.dll
xsigma.libs/svml_dispmd-c023d4ab9ddac67a1cd96ea29b1b4aff.dll
xsigma.libs/Util-1.0-dff2bf63af90fe0a97c557e0424ee538.dll
xsigma.libs/xsigmasys-dda751c9db46f38258f1ed0f82a93286.dll
xsigma.libs/xsigmaWrappingPythonCore3.10-1.0-b238990d5b57e5333b0da8222af98829.dll
xsigmamodules/all.py
xsigmamodules/Analytics.cp310-win_amd64.pyd
xsigmamodules/Analytics.pyi
xsigmamodules/Core.cp310-win_amd64.pyd
xsigmamodules/Core.pyi
xsigmamodules/generate_pyi.py
xsigmamodules/Market.cp310-win_amd64.pyd
xsigmamodules/Market.pyi
xsigmamodules/Math.cp310-win_amd64.pyd
xsigmamodules/Math.pyi
xsigmamodules/py.typed
xsigmamodules/Random.cp310-win_amd64.pyd
xsigmamodules/Random.pyi
xsigmamodules/Util.cp310-win_amd64.pyd
xsigmamodules/Util.pyi
xsigmamodules/Vectorization.cp310-win_amd64.pyd
xsigmamodules/Vectorization.pyi
xsigmamodules/__init__.py
xsigmamodules/test/BlackBox.py
xsigmamodules/test/Testing.py
xsigmamodules/test/__init__.py
xsigmamodules/util/misc.py
xsigmamodules/util/numpy_support.py
xsigmamodules/util/object_converter.py
xsigmamodules/util/xsigmaConstants.py
xsigmamodules/util/xsigmaMethodParser.py
xsigmamodules/util/__init__.py
